{
    "yasf": {
        "globals": {
            "background": {
                "r": 0.0,
                "g": 0.0,
                "b": 0.0
            },
            "ambient": {
                "r": 0.33,
                "g": 0.33,
                "b": 0.33
            },
            "fog": {
                "color": {
                    "r": 0,
                    "g": 0,
                    "b": 0
                },
                "near": 1000.0,
                "far": 2000.0
            },
            "skybox": {
                "size": {"x": 100, "y": 100, "z": 100},
                "center": {"x": 0, "y": 0, "z": 0},
                "emissive": {"r": 0, "g": 0, "b": 0},
                "intensity": 0,
                "front": "scenes/textures/skybox/front.jpg",              
                "back": "scenes/textures/skybox/back.jpg",               
                "up": "scenes/textures/skybox/up.jpg",                 
                "down": "scenes/textures/skybox/down.jpg",
                "left": "scenes/textures/skybox/left.jpg",
                "right": "scenes/textures/skybox/right.jpg"
            }
        },
        "textures": {
            "tableTop": {
                "filepath": "scenes/textures/tableTop.jpg"
            },
            "floor": {
                "filepath": "scenes/textures/floor.jpg"
            },
            "wall": {
                "filepath": "scenes/textures/wall.jpg"
            },
            "video": {
                "filepath" : "scenes/textures/pulpfiction.mp4",
                "isVideo" : true
            },
            "folder-group": {
                "filepath": "scenes/textures/folder-group.png"
            },
            "folder-black": {
                "filepath": "scenes/textures/folder-black.jpg"
            },
            "folder-blue": {
                "filepath": "scenes/textures/folder-blue.jpg"
            },
            "folder-green": {
                "filepath": "scenes/textures/folder-green.jpg"
            },
            "folder-red": {
                "filepath": "scenes/textures/folder-red.jpg"
            },
            "folder-yellow": {
                "filepath": "scenes/textures/folder-yellow.jpg"
            },
            "code": {
                "filepath": "scenes/textures/mipMapCode/code.jpg",
                "mipmap0" : "scenes/textures/mipMapCode/code1024.jpg",
                "mipmap1" : "scenes/textures/mipMapCode/code512.jpg",
                "mipmap2" : "scenes/textures/mipMapCode/code256.jpg",
                "mipmap3" : "scenes/textures/mipMapCode/code128.jpg",
                "mipmap4" : "scenes/textures/mipMapCode/code64.jpg",
                "mipmap5" : "scenes/textures/mipMapCode/code32.jpg",
                "mipmap6" : "scenes/textures/mipMapCode/code16.jpg",
                "mipmap7" : "scenes/textures/mipMapCode/code8.jpg"
                
            }
        },
        "materials": {
            "floor": {
                "color": {
                    "r": 0.8,
                    "g": 0.8,
                    "b": 0.8
                },
                "emissive": {
                    "r": 0.1,
                    "g": 0.1,
                    "b": 0.1
                },
                "specular": {
                    "r": 0.0,
                    "g": 0.0,
                    "b": 0.0
                },
                "shininess" : 0.0,
                "transparent" : false,
                "opacity" : 0,
                "textureref": "floor",
                "texlength_s": 1,
                "texlength_t": 1
            },
            "wall": {
                "color": {
                    "r": 1,
                    "g": 1,
                    "b": 1
                },
                "emissive": {
                    "r": 0.4,
                    "g": 0.4,
                    "b": 0.4
                },
                "specular": {
                    "r": 0,
                    "g": 0,
                    "b": 0
                },
                "shininess": 10,
                "transparent" : false,
                "opacity" : 0,
                "textureref": "wall",
                "texlength_s": 1,
                "texlength_t": 1
            },
            "door": {
                "color": {
                    "r": 0.7,
                    "g": 0.75,
                    "b": 0.73
                },
                "emissive": {
                    "r": 0,
                    "g": 0,
                    "b": 0
                },
                "specular": {
                    "r": 0,
                    "g": 0,
                    "b": 0
                },
                "shininess": 10,
                "transparent" : false,
                "opacity" : 0
            },
            "tableTop": {
                "color": {
                    "r": 0.8,
                    "g": 0.8,
                    "b": 0.8
                },
                "emissive": {
                    "r": 0.0,
                    "g": 0.0,
                    "b": 0.0
                },
                "specular": {
                    "r": 0.0,
                    "g": 0.0,
                    "b": 0.0
                },
                "shininess": 10,
                "transparent": false,
                "opacity": 1.0,
                "textureref": "tableTop",
                "texlength_s": 1,
                "texlength_t": 1
            },
            "tableLegBlue": {
                "color": {
                    "r": 0.2,
                    "g": 0.3,
                    "b": 0.55
                },
                "emissive": {
                    "r": 0.0,
                    "g": 0.0,
                    "b": 0.0
                },
                "specular": {
                    "r": 0.33,
                    "g": 0.33,
                    "b": 0.33
                },
                "shininess": 100,
                "transparent": false,
                "opacity": 1.0,
                "texlength_s": 1,
                "texlength_t": 1
            },
            "tableLegGrey": {
                "color": {
                    "r": 0.33,
                    "g": 0.33,
                    "b": 0.33
                },
                "emissive": {
                    "r": 0.0,
                    "g": 0.0,
                    "b": 0.0
                },
                "specular": {
                    "r": 0.33,
                    "g": 0.33,
                    "b": 0.33
                },
                "shininess": 100,
                "transparent": false,
                "opacity": 1.0,
                "texlength_s": 1,
                "texlength_t": 1
            },
            "billyMaterial" : {
                "color": {
                    "r": 0.6,
                    "g": 0.61,
                    "b": 0.58
                },
                "emissive": {
                    "r": 0.2,
                    "g": 0.2,
                    "b": 0.2
                },
                "specular": {
                    "r": 0.25,
                    "g": 0.25,
                    "b": 0.25
                },
                "shininess": 100,
                "transparent": false,
                "opacity": 0,
                "texlength_s": 1,
                "texlength_t": 1 
            },
            "frameMaterial": {
                "color": {
                    "r": 0,
                    "g": 0,
                    "b": 0
                },
                "emissive": {
                    "r": 0,
                    "g": 0,
                    "b": 0
                },
                "specular": {
                    "r": 0,
                    "g": 0,
                    "b": 0    
                },
                "shininess": 100,
                "transparent": false,
                "opacity": 1.0,
                "texlength_s": 1,
                "texlength_t": 1
            },
            "screen": {
                "color": {
                    "r": 0.1,
                    "g": 0.1,
                    "b": 0.1
                },
                "emissive": {
                    "r": 0.02,
                    "g": 0.02,
                    "b": 0.02
                },
                "specular": {
                    "r": 0.0,
                    "g": 0.0,
                    "b": 0.0
                },
                "shininess": 10,
                "transparent" : false,
                "opacity" : 0,
                "textureref": "video",
                "texlength_s": 1,
                "texlength_t": 1
            },
            "code": {
                "color": {
                    "r": 1,
                    "g": 1,
                    "b": 1
                },
                "emissive": {
                    "r": 0,
                    "g": 0,
                    "b": 0
                },
                "specular": {
                    "r": 0,
                    "g": 0,
                    "b": 0
                },
                "shininess": 10,
                "transparent" : false,
                "opacity" : 0,
                "textureref": "code",
                "texlength_s": 1,
                "texlength_t": 1
            },
            "projectorPointer": {
                "color": {
                    "r": 0.1,
                    "g": 0.3,
                    "b": 0.4
                },
                "emissive": {
                    "r": 0,
                    "g": 0,
                    "b": 0
                },
                "specular": {
                    "r": 0,
                    "g": 0,
                    "b": 0
                },
                "shininess": 10,
                "transparent": true,
                "opacity": 0.4
            },
            "projector": {
                "color": {
                    "r": 0.87,
                    "g": 0.86,
                    "b": 0.85
                },
                "emissive": {
                    "r": 0.604,
                    "g": 0.6,
                    "b": 0.58
                },
                "specular": {
                    "r": 0,
                    "g": 0,
                    "b": 0
                },
                "opacity": 1,
                "shininess": 100,
                "transparent" : false,
                "twosided" : true 
            },
            "sideSofa" : {
                "color" : {
                    "r": 1,
                    "g" : 0.99,
                    "b" : 0.94
                },
                "emissive" : {
                    "r": 0.48,
                    "g" : 0.44,
                    "b" : 0.15
                },
                "specular" : {
                    "r" : 0,
                    "g" : 0,
                    "b" : 0
                },
                "opacity" : 1,
                "shininess" : 0,
                "transparent" : false,
                "twosided" : false
            },
            "sofaMaterial" : {
                "color": {
                    "r": 0.21,
                    "g": 0.21,
                    "b": 0.21
                },
                "emissive": {
                    "r": 0,
                    "g": 0,
                    "b": 0
                },
                "specular": {
                    "r": 0.06,
                    "g": 0.06,
                    "b": 0.06
                },
                "shininess": 0,
                "transparent" : false,
                "opacity" : 1,
                "texlength_s": 1,
                "texlength_t": 1
            },
            "folder-group": {
                "color": {
                    "r": 0.8,
                    "g": 0.8,
                    "b": 0.8
                },
                "emissive": {
                    "r": 0.0,
                    "g": 0.0,
                    "b": 0.0
                },
                "specular": {
                    "r": 0.0,
                    "g": 0.0,
                    "b": 0.0
                },
                "shininess": 0,
                "transparent" : false,
                "opacity" : 1,
                "textureref": "folder-group",
                "texlength_s": 1,
                "texlength_t": 1
            },
            "folder-black": {
                "color": {
                    "r": 0.6,
                    "g": 0.6,
                    "b": 0.6
                },
                "emissive": {
                    "r": 0.0,
                    "g": 0.0,
                    "b": 0.0
                },
                "specular": {
                    "r": 0.0,
                    "g": 0.0,
                    "b": 0.0
                },
                "shininess": 0,
                "transparent" : false,
                "opacity" : 1,
                "textureref": "folder-black",
                "texlength_s": 1,
                "texlength_t": 1
            },
            "black": {
                "color": {
                    "r": 0.6,
                    "g": 0.6,
                    "b": 0.6
                },
                "emissive": {
                    "r": 0.0,
                    "g": 0.0,
                    "b": 0.0
                },
                "specular": {
                    "r": 0.0,
                    "g": 0.0,
                    "b": 0.0
                },
                "shininess": 0,
                "transparent" : false,
                "opacity" : 1,
                "texlength_s": 1,
                "texlength_t": 1
            },
            "folder-blue": {
                "color": {
                    "r": 0.8,
                    "g": 0.8,
                    "b": 1.0
                },
                "emissive": {
                    "r": 0.0,
                    "g": 0.0,
                    "b": 0.0
                },
                "specular": {
                    "r": 0.0,
                    "g": 0.0,
                    "b": 0.0
                },
                "shininess": 0,
                "transparent" : false,
                "opacity" : 1,
                "textureref": "folder-blue",
                "texlength_s": 1,
                "texlength_t": 1
            },
            "blue": {
                "color": {
                    "r": 0.8,
                    "g": 0.8,
                    "b": 1.0
                },
                "emissive": {
                    "r": 0.0,
                    "g": 0.0,
                    "b": 0.0
                },
                "specular": {
                    "r": 0.0,
                    "g": 0.0,
                    "b": 0.0
                },
                "shininess": 50,
                "transparent" : false,
                "opacity" : 1,
                "texlength_s": 1,
                "texlength_t": 1
            },
            "folder-green": {
                "color": {
                    "r": 0.8,
                    "g": 1.0,
                    "b": 0.8
                },
                "emissive": {
                    "r": 0.0,
                    "g": 0.0,
                    "b": 0.0
                },
                "specular": {
                    "r": 0.0,
                    "g": 0.0,
                    "b": 0.0
                },
                "shininess": 0,
                "transparent" : false,
                "opacity" : 1,
                "textureref": "folder-green",
                "texlength_s": 1,
                "texlength_t": 1
            },
            "green": {
                "color": {
                    "r": 0.8,
                    "g": 1.0,
                    "b": 0.8
                },
                "emissive": {
                    "r": 0.0,
                    "g": 0.0,
                    "b": 0.0
                },
                "specular": {
                    "r": 0.0,
                    "g": 0.0,
                    "b": 0.0
                },
                "shininess": 50,
                "transparent" : false,
                "opacity" : 1,
                "texlength_s": 1,
                "texlength_t": 1
            },
            "folder-red": {
                "color": {
                    "r": 1.0,
                    "g": 0.8,
                    "b": 0.8
                },
                "emissive": {
                    "r": 0.0,
                    "g": 0.0,
                    "b": 0.0
                },
                "specular": {
                    "r": 0.0,
                    "g": 0.0,
                    "b": 0.0
                },
                "shininess": 0,
                "transparent" : false,
                "opacity" : 1,
                "textureref": "folder-red",
                "texlength_s": 1,
                "texlength_t": 1
            },
            "red": {
                "color": {
                    "r": 1.0,
                    "g": 0.8,
                    "b": 0.8
                },
                "emissive": {
                    "r": 0.0,
                    "g": 0.0,
                    "b": 0.0
                },
                "specular": {
                    "r": 0.0,
                    "g": 0.0,
                    "b": 0.0
                },
                "shininess": 50,
                "transparent" : false,
                "opacity" : 1,
                "texlength_s": 1,
                "texlength_t": 1
            },
            "folder-yellow": {
                "color": {
                    "r": 1.0,
                    "g": 1.0,
                    "b": 0.8
                },
                "emissive": {
                    "r": 0.0,
                    "g": 0.0,
                    "b": 0.0
                },
                "specular": {
                    "r": 0.0,
                    "g": 0.0,
                    "b": 0.0
                },
                "shininess": 0,
                "transparent" : false,
                "opacity" : 1,
                "textureref": "folder-yellow",
                "texlength_s": 1,
                "texlength_t": 1
            },
            "yellow": {
                "color": {
                    "r": 1.0,
                    "g": 1.0,
                    "b": 0.8
                },
                "emissive": {
                    "r": 0.0,
                    "g": 0.0,
                    "b": 0.0
                },
                "specular": {
                    "r": 0.0,
                    "g": 0.0,
                    "b": 0.0
                },
                "shininess": 50,
                "transparent" : false,
                "opacity" : 1,
                "texlength_s": 1,
                "texlength_t": 1
            }
        },
        "cameras": {
            "initial": "cam1",
            "cam1": {
                "type": "perspective",
                "angle": 60,
                "near": 0.1,
                "far": 1000,
                "location": {
                    "x": 15,
                    "y": 15,
                    "z": 15
                },
                "target": {
                    "x": 0,
                    "y": 0,
                    "z": 0
                }
            },
            "cam2": {
                "type": "orthogonal",
                "near": 0.1,
                "far": 1000,
                "location": {
                    "x": 0,
                    "y": 15,
                    "z": 15
                },
                "target": {
                    "x": 0,
                    "y": 15,
                    "z": 0
                },
                "left": -5,
                "right": 5,
                "bottom": -5,
                "top": 5
            }
        },
        "graph": {
            "rootid": "scene",
            "scene": {
                "type": "node",
                "children": {
                    "pointLight": {
                        "type": "pointlight",
                        "enabled" : true,  
                        "color": {
                            "r": 0.5,
                            "g": 0.6,
                            "b": 0.8
                        },
                        "intensity": 200,
                        "distance": 1000,
                        "decay": 2.0,
                        "castshadow": false,
                        "position": {
                            "x": 0,
                            "y": 5,
                            "z": 5
                        }
                    },
                    "projectorLight" : {
                        "type": "pointlight",
                        "enabled" : true,  
                        "color": {
                            "r": 0.5,
                            "g": 0.6,
                            "b": 0.8
                        },
                        "intensity": 0.5,
                        "distance": 1,
                        "decay": 2.0,
                        "castshadow": false,
                        "position": {
                            "x": -19,
                            "y": 8.3,
                            "z": 23.1
                        }
                    },
                    "nodesList": [
                        "slimBilly",
                        "largeBilly1",
                        "largeBilly2",
                        "tableGroup1",
                        "tableGroup2",
                        "tableGroup3",
                        "walls",
                        "door",
                        "floor",
                        "projector",
                        "monitors",
                        "sofa"
                    ]
                }
            },
            "folder-group": {
                "type": "lod",
                "transforms": [
                    {
                        "type": "translate",
                        "amount": {
                            "x": 0,
                            "y": 6.8,
                            "z": 0
                        }
                    }
                ],
                "lodNodes": [
                    {
                        "nodeId": "folder-group-simple",
                        "mindist": 25
                    },
                    {
                        "nodeId": "folder-group-complex",
                        "mindist": 0
                    }
                ]
            },
            "folder-group-simple": {
                "type": "node",
                "materialref": {
                    "materialId": "folder-group"
                },
                "transforms": [
                    {
                        "type": "translate",
                        "amount": {
                            "x": 0,
                            "y": 1.25,
                            "z": 0
                        }
                    }
                ],
                "children": {
                    "boxPrim": {
                        "type": "box",
                        "xyz1": {
                            "x": 0,
                            "y": 0,
                            "z": 0
                        },
                        "xyz2": {
                            "x": 2.5,
                            "y": 2.5,
                            "z": 2
                        }
                    }
                }
            },
            "folder-group-complex": {
                "type": "node",
                "children": {
                    "nodesList": [
                        "folder-black",
                        "folder-blue",
                        "folder-green",
                        "folder-red",
                        "folder-yellow"
                    ]
                }
            },
            "folder-red": {
                "type": "node",
                "transforms": [
                    {
                        "type": "translate",
                        "amount": {
                            "x": 0,
                            "y": 0,
                            "z": 0
                        }
                    }
                ],
                "children": {
                    "nodesList": [
                        "folder-red-spine",
                        "folder-red-cover"
                    ]
                }
            },
            "folder-red-spine": {
                "type": "node",
                "transforms": [
                    {
                        "type": "translate",
                        "amount": {
                            "x": 0,
                            "y": 1.25,
                            "z": 0.96
                        }
                    }
                ],
                "materialref": {
                    "materialId": "folder-red"
                },
                "children": {
                    "boxPrim": {
                        "type": "box",
                        "xyz1": {
                            "x": 0,
                            "y": 0,
                            "z": 0
                        },
                        "xyz2": {
                            "x": 0.5,
                            "y": 2.5,
                            "z": 0.1
                        }
                    }
                }
            },
            "folder-red-cover-right": {
                "type": "node",
                "transforms": [
                    {
                        "type": "translate",
                        "amount": {
                            "x": -0.188,
                            "y": 1.25,
                            "z": 0
                        }
                    }
                ],
                "children": {
                    "boxPrim": {
                        "type": "box",
                        "xyz1": {
                            "x": 0,
                            "y": 0,
                            "z": 0
                        },
                        "xyz2": {
                            "x": 0.125,
                            "y": 2.5,
                            "z": 2
                        }
                    }
                }
            },
            "folder-red-cover-left": {
                "type": "node",
                "transforms": [
                    {
                        "type": "translate",
                        "amount": {
                            "x": 0.188,
                            "y": 1.25,
                            "z": 0
                        }
                    }
                ],
                "children": {
                    "boxPrim": {
                        "type": "box",
                        "xyz1": {
                            "x": 0,
                            "y": 0,
                            "z": 0
                        },
                        "xyz2": {
                            "x": 0.125,
                            "y": 2.5,
                            "z": 2
                        }
                    }
                }
            },
            "folder-red-cover": {
                "materialref": {
                    "materialId": "red"
                },
                "children": {
                    "nodesList": [
                        "folder-red-cover-left",
                        "folder-red-cover-right"
                    ]
                }
            },
            "folder-blue": {
                "type": "node",
                "transforms": [
                    {
                        "type": "translate",
                        "amount": {
                            "x": -1,
                            "y": 0,
                            "z": 0
                        }
                    }
                ],
                "children": {
                    "nodesList": [
                        "folder-blue-spine",
                        "folder-blue-cover"
                    ]
                }
            },
            "folder-blue-spine": {
                "type": "node",
                "transforms": [
                    {
                        "type": "translate",
                        "amount": {
                            "x": 0,
                            "y": 1.25,
                            "z": 0.96
                        }
                    }
                ],
                "materialref": {
                    "materialId": "folder-blue"
                },
                "children": {
                    "boxPrim": {
                        "type": "box",
                        "xyz1": {
                            "x": 0,
                            "y": 0,
                            "z": 0
                        },
                        "xyz2": {
                            "x": 0.5,
                            "y": 2.5,
                            "z": 0.1
                        }
                    }
                }
            },
            "folder-blue-cover-right": {
                "type": "node",
                "transforms": [
                    {
                        "type": "translate",
                        "amount": {
                            "x": -0.188,
                            "y": 1.25,
                            "z": 0
                        }
                    }
                ],
                "children": {
                    "boxPrim": {
                        "type": "box",
                        "xyz1": {
                            "x": 0,
                            "y": 0,
                            "z": 0
                        },
                        "xyz2": {
                            "x": 0.125,
                            "y": 2.5,
                            "z": 2
                        }
                    }
                }
            },
            "folder-blue-cover-left": {
                "type": "node",
                "transforms": [
                    {
                        "type": "translate",
                        "amount": {
                            "x": 0.188,
                            "y": 1.25,
                            "z": 0
                        }
                    }
                ],
                "children": {
                    "boxPrim": {
                        "type": "box",
                        "xyz1": {
                            "x": 0,
                            "y": 0,
                            "z": 0
                        },
                        "xyz2": {
                            "x": 0.125,
                            "y": 2.5,
                            "z": 2
                        }
                    }
                }
            },
            "folder-blue-cover": {
                "materialref": {
                    "materialId": "blue"
                },
                "children": {
                    "nodesList": [
                        "folder-blue-cover-left",
                        "folder-blue-cover-right"
                    ]
                }
            },
            "folder-green": {
                "type": "node",
                "transforms": [
                    {
                        "type": "translate",
                        "amount": {
                            "x": -0.5,
                            "y": 0,
                            "z": 0
                        }
                    }
                ],
                "children": {
                    "nodesList": [
                        "folder-green-spine",
                        "folder-green-cover"
                    ]
                }
            },
            "folder-green-spine": {
                "type": "node",
                "transforms": [
                    {
                        "type": "translate",
                        "amount": {
                            "x": 0,
                            "y": 1.25,
                            "z": 0.96
                        }
                    }
                ],
                "materialref": {
                    "materialId": "folder-green"
                },
                "children": {
                    "boxPrim": {
                        "type": "box",
                        "xyz1": {
                            "x": 0,
                            "y": 0,
                            "z": 0
                        },
                        "xyz2": {
                            "x": 0.5,
                            "y": 2.5,
                            "z": 0.1
                        }
                    }
                }
            },
            "folder-green-cover-right": {
                "type": "node",
                "transforms": [
                    {
                        "type": "translate",
                        "amount": {
                            "x": -0.188,
                            "y": 1.25,
                            "z": 0
                        }
                    }
                ],
                "children": {
                    "boxPrim": {
                        "type": "box",
                        "xyz1": {
                            "x": 0,
                            "y": 0,
                            "z": 0
                        },
                        "xyz2": {
                            "x": 0.125,
                            "y": 2.5,
                            "z": 2
                        }
                    }
                }
            },
            "folder-green-cover-left": {
                "type": "node",
                "transforms": [
                    {
                        "type": "translate",
                        "amount": {
                            "x": 0.188,
                            "y": 1.25,
                            "z": 0
                        }
                    }
                ],
                "children": {
                    "boxPrim": {
                        "type": "box",
                        "xyz1": {
                            "x": 0,
                            "y": 0,
                            "z": 0
                        },
                        "xyz2": {
                            "x": 0.125,
                            "y": 2.5,
                            "z": 2
                        }
                    }
                }
            },
            "folder-green-cover": {
                "materialref": {
                    "materialId": "green"
                },
                "children": {
                    "nodesList": [
                        "folder-green-cover-left",
                        "folder-green-cover-right"
                    ]
                }
            },
            "folder-yellow": {
                "type": "node",
                "transforms": [
                    {
                        "type": "translate",
                        "amount": {
                            "x": 1,
                            "y": 0,
                            "z": 0
                        }
                    }
                ],
                "children": {
                    "nodesList": [
                        "folder-yellow-spine",
                        "folder-yellow-cover"
                    ]
                }
            },
            "folder-yellow-spine": {
                "type": "node",
                "transforms": [
                    {
                        "type": "translate",
                        "amount": {
                            "x": 0,
                            "y": 1.25,
                            "z": 0.96
                        }
                    }
                ],
                "materialref": {
                    "materialId": "folder-yellow"
                },
                "children": {
                    "boxPrim": {
                        "type": "box",
                        "xyz1": {
                            "x": 0,
                            "y": 0,
                            "z": 0
                        },
                        "xyz2": {
                            "x": 0.5,
                            "y": 2.5,
                            "z": 0.1
                        }
                    }
                }
            },
            "folder-yellow-cover-right": {
                "type": "node",
                "transforms": [
                    {
                        "type": "translate",
                        "amount": {
                            "x": -0.188,
                            "y": 1.25,
                            "z": 0
                        }
                    }
                ],
                "children": {
                    "boxPrim": {
                        "type": "box",
                        "xyz1": {
                            "x": 0,
                            "y": 0,
                            "z": 0
                        },
                        "xyz2": {
                            "x": 0.125,
                            "y": 2.5,
                            "z": 2
                        }
                    }
                }
            },
            "folder-yellow-cover-left": {
                "type": "node",
                "transforms": [
                    {
                        "type": "translate",
                        "amount": {
                            "x": 0.188,
                            "y": 1.25,
                            "z": 0
                        }
                    }
                ],
                "children": {
                    "boxPrim": {
                        "type": "box",
                        "xyz1": {
                            "x": 0,
                            "y": 0,
                            "z": 0
                        },
                        "xyz2": {
                            "x": 0.125,
                            "y": 2.5,
                            "z": 2
                        }
                    }
                }
            },
            "folder-yellow-cover": {
                "materialref": {
                    "materialId": "yellow"
                },
                "children": {
                    "nodesList": [
                        "folder-yellow-cover-left",
                        "folder-yellow-cover-right"
                    ]
                }
            },
            "folder-black": {
                "type": "node",
                "transforms": [
                    {
                        "type": "translate",
                        "amount": {
                            "x": 0.5,
                            "y": 0,
                            "z": 0
                        }
                    }
                ],
                "children": {
                    "nodesList": [
                        "folder-black-spine",
                        "folder-black-cover"
                    ]
                }
            },
            "folder-black-spine": {
                "type": "node",
                "transforms": [
                    {
                        "type": "translate",
                        "amount": {
                            "x": 0,
                            "y": 1.25,
                            "z": 0.96
                        }
                    }
                ],
                "materialref": {
                    "materialId": "folder-black"
                },
                "children": {
                    "boxPrim": {
                        "type": "box",
                        "xyz1": {
                            "x": 0,
                            "y": 0,
                            "z": 0
                        },
                        "xyz2": {
                            "x": 0.5,
                            "y": 2.5,
                            "z": 0.1
                        }
                    }
                }
            },
            "folder-black-cover-right": {
                "type": "node",
                "transforms": [
                    {
                        "type": "translate",
                        "amount": {
                            "x": -0.188,
                            "y": 1.25,
                            "z": 0
                        }
                    }
                ],
                "children": {
                    "boxPrim": {
                        "type": "box",
                        "xyz1": {
                            "x": 0,
                            "y": 0,
                            "z": 0
                        },
                        "xyz2": {
                            "x": 0.125,
                            "y": 2.5,
                            "z": 2
                        }
                    }
                }
            },
            "folder-black-cover-left": {
                "type": "node",
                "transforms": [
                    {
                        "type": "translate",
                        "amount": {
                            "x": 0.188,
                            "y": 1.25,
                            "z": 0
                        }
                    }
                ],
                "children": {
                    "boxPrim": {
                        "type": "box",
                        "xyz1": {
                            "x": 0,
                            "y": 0,
                            "z": 0
                        },
                        "xyz2": {
                            "x": 0.125,
                            "y": 2.5,
                            "z": 2
                        }
                    }
                }
            },
            "folder-black-cover": {
                "materialref": {
                    "materialId": "black"
                },
                "children": {
                    "nodesList": [
                        "folder-black-cover-left",
                        "folder-black-cover-right"
                    ]
                }
            },
            "walls": {
                "type": "node",
                "materialref": {
                    "materialId": "wall"
                },
                "children": {
                    "nodesList": [
                        "wall1",
                        "wall2",
                        "wall3"
                    ]
                }

            },
            "wall1": {
                "type": "node",
                "transforms": [
                    {
                        "type": "rotate",
                        "amount": {
                            "x": 0,
                            "y": 90,
                            "z": 0
                        }
                    },
                    {
                        "type": "translate",
                        "amount": {
                            "x": 0,
                            "y": 13.5,
                            "z": -35
                        }
                    }
                ],
                "children": {
                    "nodesList": [
                        "wall"
                    ]
                }
            },
            "wall2": {
                "type": "node",
                "transforms": [
                    {
                        "type": "rotate",
                        "amount": {
                            "x": 0,
                            "y": -90,
                            "z": 0
                        }
                    },
                    {
                        "type": "translate",
                        "amount": {
                            "x": 0,
                            "y": 13.5,
                            "z": -35
                        }
                    }
                ],
                "children": {
                    "nodesList": [
                        "wall"
                    ]
                }
            },
            "wall3": {
                "type": "node",
                "transforms": [
                    {
                        "type": "rotate",
                        "amount": {
                            "x": 0,
                            "y": 180,
                            "z": 0
                        }
                    },
                    {
                        "type": "translate",
                        "amount": {
                            "x": 0,
                            "y": 13.5,
                            "z": -35
                        }
                    }
                ],
                "children": {
                    "nodesList": [
                        "wall"
                    ]
                }
            },
            "wall": {
                "type": "node",
                "children": {
                    "rectanglePrim": {
                        "type": "rectangle",
                        "xy1": {
                            "x": 0,
                            "y": 0
                        },
                        "xy2": {
                            "x": 70,
                            "y": 30
                        }
                    }
                }
            },
            "door": {
                "type": "node",
                "materialref": {
                    "materialId": "door"
                },
                "transforms": [
                    {
                        "type": "translate",
                        "amount": {
                            "x": 25,
                            "y": 11,
                            "z": 35
                        }
                    }
                ],
                "children": {
                    "boxPrim": {
                        "type": "box",
                        "xyz1": {
                            "x": 0,
                            "y": 0,
                            "z": 0
                        },
                        "xyz2": {
                            "x": 10,
                            "y": 22,
                            "z": 0.3
                        }
                    }
                }                
            },
            "floor": {
                "type": "node",
                "materialref": {
                    "materialId": "floor"
                },
                "transforms": [
                    {
                        "type": "rotate",
                        "amount": {
                            "x": -90,
                            "y": 0,
                            "z": 0
                        }
                    }
                ],
                "children": {
                    "rectanglePrim": {
                        "type": "rectangle",
                        "xy1": {
                            "x": 0,
                            "y": 0
                        },
                        "xy2": {
                            "x": 70,
                            "y": 70
                        }
                    }
                }
            },
            "tableGroup1": {
                "type": "node",
                "transforms": [
                    {
                        "type": "rotate",
                        "amount": {
                            "x": 0,
                            "y": 90,
                            "z": 0
                        }
                    },
                    {
                        "type": "translate",
                        "amount": {
                            "x": 12,
                            "y": 0,
                            "z": -27
                        }
                    }
                ],
                "children": {
                    "nodesList": [
                        "table1",
                        "table2",
                        "table3",
                        "table4",
                        "table5",
                        "table6"
                    ]
                }
            },
            "tableGroup2": {
                "type": "node",
                "transforms": [
                    {
                        "type": "rotate",
                        "amount": {
                            "x": 0,
                            "y": 90,
                            "z": 0
                        }
                    },
                    {
                        "type": "translate",
                        "amount": {
                            "x": 0,
                            "y": 0,
                            "z": -5
                        }
                    }
                ],
                "children": {
                    "nodesList": [
                        "table1",
                        "table2",
                        "table3",
                        "table4"
                    ]
                }
            },
            "tableGroup3": {
                "type": "node",
                "transforms": [
                    {
                        "type": "scale",
                        "amount": {
                            "x": 1,
                            "y": 1,
                            "z": 1.4
                        }
                    },
                    {
                        "type": "rotate",
                        "amount": {
                            "x": 0,
                            "y": 90,
                            "z": 0
                        }
                    },
                    {
                        "type": "translate",
                        "amount": {
                            "x": 0,
                            "y": 0,
                            "z": 14
                        }
                    }
                ],
                "children": {
                    "nodesList": [
                        "table1",
                        "table3"
                    ]
                }
            },
            "table1": {
                "type": "node",
                "transforms": [
                    {
                        "type": "translate",
                        "amount": {
                            "x": 0,
                            "y": 0,
                            "z": 0
                        }
                    }
                ],
                "children": {
                    "nodesList": [
                        "table"
                    ]
                }
            },
            "table2": {
                "type": "node",
                "transforms": [
                    {
                        "type": "rotate",
                        "amount": {
                            "x": 0,
                            "y": 180,
                            "z": 0
                        }
                    },
                    {
                        "type": "translate",
                        "amount": {
                            "x": 12,
                            "y": 0,
                            "z": -13.8
                        }
                    }
                ],
                "children": {
                    "nodesList": [
                        "table"
                    ]
                }
            },
            "table3": {
                "type": "node",
                "transforms": [
                    {
                        "type": "translate",
                        "amount": {
                            "x": -12,
                            "y": 0,
                            "z": 0
                        }
                    }
                ],
                "children": {
                    "nodesList": [
                        "table"
                    ]
                }
            },
            "table4": {
                "type": "node",
                "transforms": [
                    {
                        "type": "rotate",
                        "amount": {
                            "x": 0,
                            "y": 180,
                            "z": 0
                        }
                    },
                    {
                        "type": "translate",
                        "amount": {
                            "x": 24,
                            "y": 0,
                            "z": -13.8
                        }
                    }
                ],
                "children": {
                    "nodesList": [
                        "table"
                    ]
                }
            },
            "table5": {
                "type": "node",
                "transforms": [
                    {
                        "type": "translate",
                        "amount": {
                            "x": -24,
                            "y": 0,
                            "z": 0
                        }
                    }
                ],
                "children": {
                    "nodesList": [
                        "table"
                    ]
                }
            },
            "table6": {
                "type": "node",
                "transforms": [
                    {
                        "type": "rotate",
                        "amount": {
                            "x": 0,
                            "y": 180,
                            "z": 0
                        }
                    },
                    {
                        "type": "translate",
                        "amount": {
                            "x": 36,
                            "y": 0,
                            "z": -13.8
                        }
                    }
                ],
                "children": {
                    "nodesList": [
                        "table"
                    ]
                }
            },
            "table": {
                "type": "node",
                "transforms": [
                    {
                        "type": "translate",
                        "amount": {
                            "x": -6,
                            "y": 0,
                            "z": 3
                        }
                    }
                ],
                "children": {
                    "nodesList": [
                        "tableTop", 
                        "rightLeg", 
                        "leftLeg"   
                    ]
                }
            },
            "largeBilly1": {
                "type": "node",
                "transforms": [
                    {
                        "type": "scale",
                        "amount": {
                            "x": 2,
                            "y": 1,
                            "z": 1
                        }
                    },
                    {
                        "type": "rotate",
                        "amount": {
                            "x": 0,
                            "y": -90,
                            "z": 0
                        }
                    },
                    {
                        "type": "translate",
                        "amount": {
                            "x": 0,
                            "y": 0,
                            "z": -33
                        }
                    }
                ],
                "children": {
                    "nodesList": [
                        "billy"
                    ]
                }
            },
            "largeBilly2": {
                "type": "node",
                "transforms": [
                    {
                        "type": "scale",
                        "amount": {
                            "x": 2,
                            "y": 1,
                            "z": 1
                        }
                    },
                    {
                        "type": "rotate",
                        "amount": {
                            "x": 0,
                            "y": -90,
                            "z": 0
                        }
                    },
                    {
                        "type": "translate",
                        "amount": {
                            "x": 9,
                            "y": 0,
                            "z": -33
                        }
                    }
                ],
                "children": {
                    "nodesList": [
                        "billy"
                    ]
                }
            },
            "slimBilly": {
                "type": "node",
                "transforms": [
                    {
                        "type": "translate",
                        "amount": {
                            "x": 0,
                            "y": 0,
                            "z": -33
                        }
                    }
                ],
                "children": {
                    "nodesList": [
                        "billy"
                    ],
                    "lodsList": [
                        "folder-group"
                    ]
                }
            },
            "billy": {
                "type": "node",
                "materialref": {
                    "materialId": "billyMaterial"
                },
                "children": {
                    "nodesList": [
                        "billyVertical",
                        "billyLateral",
                        "billyBack",
                        "billyMiddles"
                    ]
                }
            },
            "billyMiddles" : {
                "type" : "node",
                "children" : {
                    "nodesList": [
                        "billyMiddle1",
                        "billyMiddle2",
                        "billyMiddle3",
                        "billyMiddle4",
                        "billyMiddle5"
                    ]
                }
            },
            "billyMiddle1" : {
                "type": "node",
                "transforms": [
                    {
                        "type": "translate",
                        "amount": {
                            "x": 0,
                            "y": 17,
                            "z": 0
                        }
                    }
                ],
                "children": {
                    "nodesList": [
                        "shelf"
                    ]
                }
            },
            "billyMiddle2" : {
                "type": "node",
                "transforms": [
                    {
                        "type": "translate",
                        "amount": {
                            "x": 0,
                            "y": 13.6,
                            "z": 0
                        }
                    }
                ],
                "children": {
                    "nodesList": [
                        "shelf"
                    ]
                }
            },
            "billyMiddle3" : {
                "type": "node",
                "transforms": [
                    {
                        "type": "translate",
                        "amount": {
                            "x": 0,
                            "y": 10.2,
                            "z": 0
                        }
                    }
                ],
                "children": {
                    "nodesList": [
                        "shelf"
                    ]
                }
            },
            "billyMiddle4" : {
                "type": "node",
                "transforms": [
                    {
                        "type": "translate",
                        "amount": {
                            "x": 0,
                            "y": 6.8,
                            "z": 0
                        }
                    }
                ],
                "children": {
                    "nodesList": [
                        "shelf"
                    ]
                }
            },
            "billyMiddle5" : {
                "type": "node",
                "transforms": [
                    {
                        "type": "translate",
                        "amount": {
                            "x": 0,
                            "y": 3.4,
                            "z": 0
                        }
                    }
                ],
                "children": {
                    "nodesList": [
                        "shelf"
                    ]
                }
            },
            "shelf": {
                "type": "node",
                "children": {
                    "boxPrim": {
                        "type": "box",
                        "xyz1": {
                            "x": 0,
                            "y": 0,
                            "z": 0
                        },
                        "xyz2": {
                            "x": 4,
                            "y": 0.125,
                            "z": 4
                        }
                    }
                }
            },
            "billyBack" : {
                "type" : "node",
                "transforms": [
                    {
                        "type": "translate",
                        "amount": {
                            "x": 0,
                            "y": 10.1,
                            "z": -1.84375
                        }
                    }
                ],
                "children": {
                    "boxPrim": {
                        "type": "box",
                        "xyz1": {
                            "x": 0,
                            "y": 0,
                            "z": 0
                        },
                        "xyz2": {
                            "x": 4,
                            "y": 20.2,
                            "z": 0.3125
                        }
                    }
                }
            },
            "billyLateral" : {
                "type" : "node",
                "children" : {
                    "nodesList": [
                        "billyLeft",
                        "billyRight"
                    ]
                }
            },
            "billyLeft" : {
                "type": "node",
                "transforms": [
                    {
                        "type": "translate",
                        "amount": {
                            "x": -1.84375,
                            "y": 10.1,
                            "z": 0
                        }
                    }
                ],
                "children": {
                    "boxPrim": {
                        "type": "box",
                        "xyz1": {
                            "x": 0,
                            "y": 0,
                            "z": 0
                        },
                        "xyz2": {
                            "x": 0.3125,
                            "y": 20.2,
                            "z": 4
                        }
                    }
                }
            },
            "billyRight" : {
                "type": "node",
                "transforms": [
                    {
                        "type": "translate",
                        "amount": {
                            "x": 1.84375,
                            "y": 10.1,
                            "z": 0
                        }
                    }
                ],
                "children": {
                    "boxPrim": {
                        "type": "box",
                        "xyz1": {
                            "x": 0,
                            "y": 0,
                            "z": 0
                        },
                        "xyz2": {
                            "x": 0.3125,
                            "y": 20.2,
                            "z": 4
                        }
                    }
                }
            },
            "billyVertical": {
                "type": "node",
                "children": {
                    "nodesList": [
                        "billyBase",
                        "billyTop"
                    ]
                }
            },
            "billyBase" : {
                "type": "node",
                "transforms": [
                    {
                        "type": "translate",
                        "amount": {
                            "x": 0,
                            "y": 0.3125,
                            "z": 0
                        }
                    }
                ],
                "children": {
                    "boxPrim": {
                        "type": "box",
                        "xyz1": {
                            "x": 0,
                            "y": 0,
                            "z": 0
                        },
                        "xyz2": {
                            "x": 4,
                            "y": 0.625,
                            "z": 4
                        }
                    }
                }
            },
            "billyTop" : {
                "type": "node",
                "transforms": [
                    {
                        "type": "translate",
                        "amount": {
                            "x": 0,
                            "y": 20.2,
                            "z": 0
                        }
                    }
                ],
                "children": {
                    "boxPrim": {
                        "type": "box",
                        "xyz1": {
                            "x": 0,
                            "y": 0,
                            "z": 0
                        },
                        "xyz2": {
                            "x": 4,
                            "y": 0.625,
                            "z": 4
                        }
                    }
                }
            },
            "tableTop": {
                "type": "node",
                "materialref": {
                    "materialId": "tableTop"
                },
                "transforms": [
                    {
                        "type": "translate",
                        "amount": {
                            "x": 0,
                            "y": 7.7,
                            "z": 0.9
                        }
                    }
                ],
                "children": {
                    "boxPrim": {
                        "type": "box",
                        "xyz1": {
                            "x": 0,
                            "y": 0,
                            "z": 0
                        },
                        "xyz2": {
                            "x": 12,
                            "y": 0.3,
                            "z": 6
                        }
                    }
                }
            },
            "rightLeg": {
                "type": "node",
                "transforms": [
                    {
                        "type": "translate",
                        "amount": {
                            "x": 5.5,
                            "y": 0,
                            "z": 0
                        }
                    }
                ],
                "children": {
                    "nodesList": [
                        "tableLeg"
                    ]
                }
            },
            "leftLeg": {
                "type": "node",
                "transforms": [
                    {
                        "type": "translate",
                        "amount": {
                            "x": -5.5,
                            "y": 0,
                            "z": 0
                        }
                    }
                ],
                "children": {
                    "nodesList": [
                        "tableLeg"
                    ]
                }
            },
            "tableLeg": {
                "type": "node",
                "children": {
                    "nodesList": [
                        "tableLegCenter",
                        "tableLegSide1",
                        "tableLegSide2",
                        "tableLegSupport"
                    ]
                }
            },
            "tableLegCenter": {
                "type": "node",
                "materialref": {
                    "materialId": "tableLegGrey"
                },
                "transforms": [
                    {
                        "type": "translate",
                        "amount": {
                            "x": 0,
                            "y": 3.85,
                            "z": 0.9
                        }
                    },
                    {
                        "type": "scale",
                        "amount": {
                            "x": 0.3,
                            "y": 1,
                            "z": 1.5
                        }
                    }
                ],
                "children": {
                    "cylinderPrim": {
                        "type": "cylinder",
                        "height": 7.7,
                        "top": 0.5,
                        "base": 0.5
                    }
                }
            },
            "tableLegSide1": {
                "type": "node",
                "materialref": {
                    "materialId": "tableLegBlue"
                },
                "transforms": [
                    {
                        "type": "translate",
                        "amount": {
                            "x": 0,
                            "y": 3.85,
                            "z": 1.65
                        }
                    }
                ],
                "children": {
                    "cylinderPrim": {
                        "type": "cylinder",
                        "height": 7.7,
                        "top": 0.3,
                        "base": 0.3
                    }
                }
            },
            "tableLegSide2": {
                "type": "node",
                "materialref": {
                    "materialId": "tableLegBlue"
                },
                "transforms": [
                    {
                        "type": "translate",
                        "amount": {
                            "x": 0,
                            "y": 3.85,
                            "z": 0.25
                        }
                    }
                ],
                "children": {
                    "cylinderPrim": {
                        "type": "cylinder",
                        "height": 7.7,
                        "top": 0.3,
                        "base": 0.3
                    }
                }
            },
            "tableLegSupport": {
                "type": "node",
                "materialref": {
                    "materialId": "tableLegBlue"
                },
                "transforms": [
                    {
                        "type": "translate",
                        "amount": {
                            "x": 0,
                            "y": 0.2,
                            "z": 0.45
                        }
                    }
                ],
                "children": {
                    "boxPrim": {
                        "type": "box",
                        "xyz1": {
                            "x": 0,
                            "y": 0,
                            "z": 0
                        },
                        "xyz2": {
                            "x": 1,
                            "y": 0.4,
                            "z": 6.9
                        }
                    }
                }
            },
            "projector" :{
                "type" : "node",
                "materialref": {
                    "materialId": "projector"
                },
                "children" : {
                    "nodesList" : [
                        "projectorCase",
                        "projectorPointer",
                        "projectorPointerCase",
                        "projectorScreen"
                    ]
                }
                
            },                  
            "projectorCase" : {
                "type" : "node",
                "transforms" : [
                    {
                        "type": "translate",
                        "amount": {
                            "x": -20,
                            "y": 8.3,
                            "z": 21  
                        }
                    }
                ],
                "children" : {
                    "boxPrim": {
                        "type" : "box",
                        "xyz1" : {
                            "x" : 0,
                            "y" : 0,
                            "z" : 0
                        },
                        "xyz2" : {
                            "x" : 4,
                            "y" : 1,
                            "z": 3
                        }
                    }
                }
            },
            "projectorPointer" : {
                "type": "node",
                "materialref": {
                    "materialId": "projectorPointer"
                },
                "transforms" : [
                    {
                        "type": "translate",
                        "amount": {
                            "x": -19,
                            "y": 8.3,
                            "z": 22.5  
                        }
                    }
                ],
                "children" : {
                    "spherePrim": {
                        "type": "sphere",
                        "radius" : 0.3
                    }
                }   
            },
            "projectorPointerCase" : {
                "type": "node",
                "transforms" : [
                    {
                        "type": "translate",
                        "amount": {
                            "x": -19,
                            "y": 8.3,
                            "z": 22.5  
                        }
                    },
                    {
                        "type": "rotate",
                        "amount": {
                            "x": -90,
                            "y": 0,
                            "z": 0
                        }
                    }
                ],
                "children" : {
                    "cylinderPrim": {
                        "type": "cylinder",
                        "base" : 0.2,
                        "top": 0.4,
                        "slices" : 32,
                        "stacks" : 1,
                        "height" : 0.8,
                        "capsclose" : false

                    }
                }   
            },
            "projectorScreen" : {
                "type": "node",
                "materialref": {
                    "materialId": "screen"
                },
                "transforms": [
                    {
                        "type": "rotate",
                        "amount": {
                            "x": 0,
                            "y": 180,
                            "z": 0
                        }
                    },
                    {
                        "type": "translate",
                        "amount": {
                            "x": 20,
                            "y": 15,
                            "z": -34.5
                        }
                    }
                ],
                "children": {
                    "rectanglePrim": {
                        "type": "rectangle",
                        "xy1": {
                            "x": 0,
                            "y": 0
                        },
                        "xy2": {
                            "x": 15,
                            "y": 15
                        }
                    }
                }
            },
            "monitors" : {
                "type" : "node",
                "children" : {
                    "nodesList" : [
                        "monitor",
                        "monitor1",
                        "monitor2"
                    ]
                }
            },
            "monitor" : {
                "type" : "node",
                "materialref" : {
                    "materialId" : "frameMaterial"
                },
                "transforms": [
                    {
                        "type": "translate",
                        "amount": {
                            "x": 0,
                            "y": 0,
                            "z": 20
                        }
                    },
                    {
                        "type" : "rotate",
                        "amount": {
                            "x": 0,
                            "y": 90,
                            "z": 0  
                        }
                    }
                ],
                "children" : {
                    "nodesList" : [
                        "base",
                        "monitorSupport",
                        "monitorFrame"
                    ]
                }
            },
            "monitor1" : {
                "type" : "node",
                "materialref" : {
                    "materialId" : "frameMaterial"
                },
                "transforms": [
                    {
                        "type": "translate",
                        "amount": {
                            "x": 0,
                            "y": 0,
                            "z": 7
                        }
                    },
                    {
                        "type" : "rotate",
                        "amount": {
                            "x": 0,
                            "y": 90,
                            "z": 0  
                        }
                    }
                ],
                "children" : {
                    "nodesList" : [
                        "base",
                        "monitorSupport",
                        "monitorFrame"
                    ]
                }
            },
            "monitor2" : {
                "type" : "node",
                "transforms": [
                    {
                        "type": "translate",
                        "amount": {
                            "x": -22,
                            "y": 0,
                            "z": 12
                        }
                    },
                    {
                        "type" : "rotate",
                        "amount": {
                            "x": 0,
                            "y": 90,
                            "z": 0  
                        }
                    }
                ],
                "materialref" : {
                    "materialId" : "frameMaterial"
                },
                "children" : {
                    "nodesList" : [
                        "base",
                        "monitorSupport",
                        "monitorFrame"
                    ]
                }
            },
            "base" : {
                "type" : "node",
                "transforms": [
                    {
                        "type": "translate",
                        "amount": {
                            "x": 0,
                            "y": 8,
                            "z": 0
                        }
                    }
                ],
                 "children" : {
                    "boxPrim" : {
                        "type" : "box",
                        "xyz1" : {
                            "x" : 0,
                            "y" : 0,
                            "z" : 0
                        },
                        "xyz2" : {
                            "x" : 2,
                            "y" : 0.2,
                            "z": 1.4
                        }
                    }
                }
            },
            "monitorSupport" : {
                "type" : "node",
                "transforms": [
                    {
                        "type": "translate",
                        "amount": {
                            "x": 0,
                            "y": 8.5,
                            "z": 0
                        }
                    }
                ],
                 "children" : {
                    "cylinderPrim" : {
                        "type" : "cylinder",
                        "height": 1,
                        "top": 0.15,
                        "base": 0.15
                    }
                }
            },
            "monitorFrame" : {
                "type" : "node",
                "transforms" : [
                    {
                        "type": "translate",
                        "amount": {
                            "x": 0,
                            "y": 9,
                            "z": 0
                        }
                    }
                ],
                "children" : {
                    "nodesList": [
                        "monitorBot", 
                        "monitorLeft",
                        "monitorRight",
                        "monitorTop",
                        "monitorBack",
                        "screen"
                    ]
                }
            },
            "screen" : {
                "type" : "node",
                "materialref": {
                    "materialId": "code"
                },
                "transforms": [
                    {
                        "type": "rotate",
                        "amount": {
                            "x": 0,
                            "y": 180,
                            "z": 0
                        }

                    },
                    {
                        "type": "translate",
                        "amount": {
                            "x": 0,
                            "y": 2,
                            "z": 0.2
                        }
                    }
                ],
                 "children" : {
                    "rectanglePrim" : {
                        "type" : "rectangle",
                        "xy1" : {
                            "x" : 0,
                            "y" : 0
                        },
                        "xy2" : {
                            "x" : 6,
                            "y" : 4
                        }
                    }
                }
            },
            "monitorBack" : {
                "type" : "node",
                "transforms": [
                    {
                        "type": "translate",
                        "amount": {
                            "x": 0,
                            "y": 2,
                            "z": 0
                        }
                    }
                ],
                 "children" : {
                    "rectanglePrim" : {
                        "type" : "rectangle",
                        "xy1" : {
                            "x" : 0,
                            "y" : 0
                        },
                        "xy2" : {
                            "x" : 6,
                            "y" : 4
                        }
                    }
                }
            },
            "monitorBot" : {
                "type" : "node",
                "transforms": [
                    {
                        "type": "translate",
                        "amount": {
                            "x": 0,
                            "y": 0.1,
                            "z": 0
                        }
                    }
                ],
                 "children" : {
                    "boxPrim" : {
                        "type" : "box",
                        "xyz1" : {
                            "x" : 0,
                            "y" : 0,
                            "z" : 0
                        },
                        "xyz2" : {
                            "x" : 6,
                            "y" : 0.2,
                            "z": 0.8
                        }
                    }
                }
            },
            "monitorTop" : {
                "type" : "node",
                "transforms": [
                    {
                        "type": "translate",
                        "amount": {
                            "x": 0,
                            "y": 4,
                            "z": 0
                        }
                    }
                ],
                 "children" : {
                    "boxPrim" : {
                        "type" : "box",
                        "xyz1" : {
                            "x" : 0,
                            "y" : 0,
                            "z" : 0
                        },
                        "xyz2" : {
                            "x" : 6.2,
                            "y" : 0.2,
                            "z": 0.8
                        }
                    }
                }
            },
            "monitorLeft" : {
                "type" : "node",
                "transforms": [
                    {
                        "type": "translate",
                        "amount": {
                            "x": -3,
                            "y": 2,
                            "z": 0
                        }
                    }
                ],
                 "children" : {
                    "boxPrim" : {
                        "type" : "box",
                        "xyz1" : {
                            "x" : 0,
                            "y" : 0,
                            "z" : 0
                        },
                        "xyz2" : {
                            "x" : 0.2,
                            "y" : 4,
                            "z": 0.8
                        }
                    }
                }
            },
            "monitorRight" : {
                "type" : "node",
                "transforms": [
                    {
                        "type": "translate",
                        "amount": {
                            "x": 3,
                            "y": 2,
                            "z": 0
                        }
                    }
                ],
                 "children" : {
                    "boxPrim" : {
                        "type" : "box",
                        "xyz1" : {
                            "x" : 0,
                            "y" : 0,
                            "z" : 0
                        },
                        "xyz2" : {
                            "x" : 0.2,
                            "y" : 4,
                            "z": 0.8
                        }
                    }
                }
            },
            "sofa" : {
                "type" : "node",
                "materialref" : {
                    "materialId" : "sofaMaterial"
                },
                "children" : {
                    "nodesList" : [
                        "bases",
                        "sofaLegs",
                        "sides"
                    ]
                }
            },
            "bases" : {
                "type" : "node",
                "children" : {
                    "nodesList" : [
                        "backBase",
                        "underBase"
                    ]
                }
            },
            "underBase" : {
                "type": "node",
                "transforms": [
                    {
                        "type": "translate",
                        "amount": {
                            "x": 14,
                            "y": 2,
                            "z": -20
                        }
                    }
                ],
                 "children" : {
                    "boxPrim" : {
                        "type" : "box",
                        "xyz1" : {
                            "x" : 0,
                            "y" : 0,
                            "z" : 0
                        },
                        "xyz2" : {
                            "x" : 8,
                            "y" : 2.1,
                            "z": 15
                        }
                    }
                }
            },
            "backBase" : {
                "type": "node",
                "transforms": [
                    {
                        "type" : "translate",
                        "amount" : {
                            "x" : 10,
                            "y" : 5,
                            "z" : -20
                        }
                    },
                    {
                        "type" : "rotate",
                        "amount" : {
                            "x": 0,
                            "y": 0,
                            "z": -60
                        }
                    }
                ],
                 "children" : {
                    "boxPrim" : {
                        "type" : "box",
                        "xyz1" : {
                            "x" : 0,
                            "y" : 0,
                            "z" : 0
                        },
                        "xyz2" : {
                            "x" : 6,
                            "y" : 2.1,
                            "z": 15
                        }
                    }
                }
            },
            "sofaLegs" : {
                "type": "node",
                "children" : {
                    "nodesList" : [
                        "sofaLeg1",
                        "sofaLeg2",
                        "sofaLeg3",
                        "sofaLeg4"

                    ]
                }
            },
            "sofaLeg1" : {
                "type": "node",
                "transforms" : [
                    {
                        "type" : "translate",
                        "amount" : {
                            "x" : 11,
                            "y" : 0.5,
                            "z" : -13.5
                        }
                    }
                ],
                "children" : {
                    "cylinderPrim": {
                        "type": "cylinder",
                        "height": 1,
                        "top": 0.1,
                        "base": 0.2
                    }
                }
            },
            "sofaLeg2" : {
                "type": "node",
                "transforms" : [
                    {
                        "type" : "translate",
                        "amount" : {
                            "x" : 17,
                            "y" : 0.5,
                            "z" : -13.5
                        }
                    }
                ],
                "children" : {
                    "cylinderPrim": {
                        "type": "cylinder",
                        "height": 1,
                        "top": 0.1,
                        "base": 0.2
                    }
                }
            },
            "sofaLeg3" : {
                "type": "node",
                "transforms" : [
                    {
                        "type" : "translate",
                        "amount" : {
                            "x" : 17,
                            "y" : 0.5,
                            "z" : -27
                        }
                    }
                ],
                "children" : {
                    "cylinderPrim": {
                        "type": "cylinder",
                        "height": 1,
                        "top": 0.1,
                        "base": 0.2
                    }
                }
            },
            "sofaLeg4" : {
                "type": "node",
                "transforms" : [
                    {
                        "type" : "translate",
                        "amount" : {
                            "x" : 11,
                            "y" : 0.5,
                            "z" : -27
                        }
                    }
                ],
                "children" : {
                    "cylinderPrim": {
                        "type": "cylinder",
                        "height": 1,
                        "top": 0.1,
                        "base": 0.2
                    }
                }
            },
            "sides" : {
                "type": "node",
                "materialref" : {
                    "materialId" : "sideSofa"
                },
                "children" : {
                    "nodesList" :[
                        "sofaSide1",
                        "sofaSide2",
                        "sofaSide3",
                        "sofaSide4"
                    ]
                }
            },
            "sofaSide1" : {
                "type" : "node",
                "transforms" : [
                    {
                        "type" : "translate",
                        "amount" : {
                            "x" : 10,
                            "y" : 5,
                            "z" : -13
                        }
                    },
                    {
                        "type" : "rotate",
                        "amount" : {
                            "x": 0,
                            "y": 0,
                            "z": 30
                        }
                    }
                ],
                "children" : {
                    "cylinderPrim": {
                        "type": "cylinder",
                        "height": 5.99,
                        "top": 1,
                        "base": 1,
                        "capsclose" : true
                    }
                }
            },
            "sofaSide2" : {
                "type" : "node",
                "transforms" : [
                    {
                        "type" : "translate",
                        "amount" : {
                            "x" : 10,
                            "y" : 5,
                            "z" : -27
                        }
                    },
                    {
                        "type" : "rotate",
                        "amount" : {
                            "x": 0,
                            "y": 0,
                            "z": 30
                        }
                    }
                ],
                "children" : {
                    "cylinderPrim": {
                        "type": "cylinder",
                        "height": 5.99,
                        "top": 1,
                        "base": 1,
                        "capsclose" : true
                    }
                }
            },
            "sofaSide3" : {
                "type" : "node",
                "transforms" : [
                    {
                        "type" : "translate",
                        "amount" : {
                            "x" : 14,
                            "y" : 2,
                            "z" : -13
                        }
                    },
                    {
                        "type" : "rotate",
                        "amount" : {
                            "x": 0,
                            "y": 0,
                            "z": 90
                        }
                    }
                ],
                "children" : {
                    "cylinderPrim": {
                        "type": "cylinder",
                        "height": 7.99,
                        "top": 1,
                        "base": 1,
                        "capsclose" : true
                    }
                }
            },
            "sofaSide4" : {
                "type" : "node",
                "transforms" : [
                    {
                        "type" : "translate",
                        "amount" : {
                            "x" : 14,
                            "y" : 2,
                            "z" : -27
                        }
                    },
                    {
                        "type" : "rotate",
                        "amount" : {
                            "x": 0,
                            "y": 0,
                            "z": 90
                        }
                    }
                ],
                "children" : {
                    "cylinderPrim": {
                        "type": "cylinder",
                        "height": 7.99,
                        "top": 1,
                        "base": 1,
                        "capsclose" : true
                    }
                }
            }
        }
    }
}